Workbook

Sheet 1_Payslip_120k net
C3: Name | D3: =Payroll_Raw!D7 -> 0
C4: Staff Code | D4: =Payroll_Raw!F7 -> 0
C5: Location | D5: =Payroll_Raw!E7 -> 0
C6: Designation | D6: =Payroll_Raw!G7 -> 0
C8: Month
C9: Year | D9: 2022
B11: Description | C11: N | D11: N
B13: (A) Components of Salary
B14: Basic Salary | C14: =Payroll_Raw!S7 -> 442136.6
B15: Housing Allowance | C15: =Payroll_Raw!J7/12 -> 0
B16: Transport Allowance | C16: =Payroll_Raw!K7/12 -> 0
B17: Others | C17: =SUM(Payroll_Raw!L7:Q7)/12 -> 0
B22: Gross Remuneration | C22: =SUM(C14:C21) -> 442136.6 | D22: =C22 -> 442136.6
B23: (B) Other Benefits
B24: Less: Deductions
B25: Non-Statutory
B26: Lateness
B27: Loan
B28: Total Non-Statutory Deductions | C28: =SUM(C26:C27) -> 0 | D28: =-C28 -> 0
B30: Statutory Deductions
B31: PAYE | C31: =PAYE!AC9 -> 56765.676
B32: Pension | C32: =PAYE!AE9 -> 35370.928
B33: NHIS
B34: NSITF
B35: Total Statutory Deductions | C35: =SUM(C31:C34) -> 92136.604 | D35: =-C35 -> -92136.604
B38: Net Pay | D38: =SUM(D22:D35) -> 350000
B40: Prepared by: | D40: Approved by:
B41: Name: | D41: Name:
B42: Designation: | D42: Designation:
B43: Date | D43: Date
B44: Signature | D44: Signature

Sheet 2_Payslip_150k net
C3: Name | D3: =Payroll_Raw!D8 -> 0
C4: Staff Code | D4: =Payroll_Raw!F8 -> 0
C5: Location | D5: =Payroll_Raw!E8 -> 0
C6: Designation | D6: =Payroll_Raw!G8 -> 0
C8: Month
C9: Year | D9: 2022
B11: Description | C11: N | D11: N
B13: (A) Components of Salary
B14: Basic Salary | C14: =Payroll_Raw!S8 -> 179664
B15: Housing Allowance | C15: =Payroll_Raw!J8/12 -> 0
B16: Transport Allowance | C16: =Payroll_Raw!K8/12 -> 0
B17: Others | C17: =SUM(Payroll_Raw!L8:Q8)/12 -> 0
B22: Gross Remuneration | C22: =SUM(C14:C21) -> 179664 | D22: =C22 -> 179664
B23: (B) Other Benefits | C23: -
B24: Less: Deductions
B25: Non-Statutory
B26: Lateness
B27: Loan
B28: Total Non-Statutory Deductions | C28: =SUM(C26:C27) -> 0 | D28: =-C28 -> 0
B30: Statutory Deductions
B31: PAYE | C31: =PAYE!AC10 -> 7511.3631
B32: Pension | C32: =PAYE!AE10 -> 9428.524
B33: NHIS | C33: -
B34: NSITF | C34: -
B35: Total Statutory Deductions | C35: =SUM(C31:C34) -> 16939.887 | D35: =-C35 -> -16939.887
B38: Net Pay | D38: =SUM(D22:D35) -> 162724.11
B40: Prepared by: | D40: Approved by:
B41: Name: | D41: Name:
B42: Designation: | D42: Designation:
B43: Date | D43: Date
B44: Signature | D44: Signature

Sheet 3_Payslip_200k net
C3: Name | D3: =Payroll_Raw!D9 -> 0
C4: Staff Code | D4: =Payroll_Raw!F9 -> 0
C5: Location | D5: =Payroll_Raw!E9 -> 0
C6: Designation | D6: =Payroll_Raw!G9 -> 0
C8: Month
C9: Year | D9: 2022
B11: Description | C11: N | D11: N
B13: (A) Components of Salary
B14: Basic Salary | C14: =Payroll_Raw!S9 -> 244521.67
B15: Housing Allowance | C15: =Payroll_Raw!J9/12 -> 0
B16: Transport Allowance | C16: =Payroll_Raw!K9/12 -> 0
B17: Others | C17: =SUM(Payroll_Raw!L9:Q9)/12 -> 0
B22: Gross Remuneration | C22: =SUM(C14:C21) -> 244521.67 | D22: =C22 -> 244521.67
B23: (B) Other Benefits | C23: -
B24: Less: Deductions
B25: Non-Statutory
B26: Lateness
B27: Loan
B28: Total Non-Statutory Deductions | C28: =SUM(C26:C27) -> 0 | D28: =-C28 -> 0
B30: Statutory Deductions
B31: PAYE | C31: =PAYE!AC11 -> 24959.936
B32: Pension | C32: =PAYE!AE11 -> 19561.734
B33: NHIS | C33: -
B34: NSITF | C34: -
B35: Total Statutory Deductions | C35: =SUM(C31:C34) -> 44521.67 | D35: =-C35 -> -44521.67
B38: Net Pay | D38: =SUM(D22:D35) -> 200000
B40: Prepared by: | D40: Approved by:
B41: Name: | D41: Name:
B42: Designation: | D42: Designation:
B43: Date | D43: Date
B44: Signature | D44: Signature

Sheet Payroll_Raw
I4: If Pension is computed on Gross
C5: S/N | D5: NAME | E5: Staff Location | F5: Staff Code | G5: DESIGNATION | I5: Basic | R5: Annual Gross Total | S5: Monthly Gross Total
I6: N | J6: N | K6: N | L6: N | M6: N | N6: N | O6: N | P6: N | Q6: N | R6: N | S6: N
A7: =PAYE!AA9-350000 -> -0.0036906667 | B7: 442136.6 | C7: 1 | H7: 12 | I7: =B7*H7 -> 5305639.2 | R7: =B7*H7 -> 5305639.2 | S7: =R7/H7 -> 442136.6
A8: =PAYE!AA10-150000 -> -49083.337 | B8: 179664 | C8: 2 | H8: 12 | R8: =B8*H8 -> 2155968 | S8: =R8/H8 -> 179664
A9: =PAYE!AA11-200000 -> 0.00041813334 | B9: 244521.67 | C9: 3 | H9: 12 | R9: =B9*H9 -> 2934260 | S9: =R9/H9 -> 244521.67
C10: 4 | H10: 12 | R10: =B10*H10 -> 0 | S10: =R10/H10 -> 0
C11: 5
C12: 6
C13: 7
C14: 8
C15: 9
C16: 10
C17: 11
C18: 12
C19: 13
C20: 14
C21: 14
C22: 16
... C29: 23

Sheet PAYE
B2: Finsilver Global Limited
F5: =F9/12 -> 442136.6 | L5: TAX RATE | X5: EXPECTED ANNUAL PAYE DEDUCTION | Z5: NET PAY | AB5: PAYE | AD5: Pension- Employee Contribution | AF5: Pension- Employer Contribution | AH5: Total Pension- Contribution
B6: S/N | D6: NAME | F6: Gross Annual Pay | G6: EXEMPTIONS | H6: NET INCOME | I6: CONSOLIDATED RELIEF ALLOWANCE | J6: TAX FREE PAY | K6: TAXABLE INCOME | L6: FIRST N300,000 | N6: NEXT N300,000 | P6: NEXT N500,000 | R6: NEXT N500,000 | T6: NEXT N1,600,000 | V6: ABOVE N3,200,000 | X6: MINIMUM TAX | Y6: COMPUTED | Z6: Annual | AA6: Monthly | AB6: Annual | AC6: Monthly | AD6: Annual | AE6: Monthly | AF6: Annual | AG6: Monthly | AH6: Annual | AI6: Monthly
G7: PENSION | X7: 0.01
G8: N | H8: N | I8: N | J8: N | K8: N | L8: % | M8: N | N8: % | O8: N | P8: % | Q8: N | R8: % | S8: N | T8: % | U8: N | V8: % | W8: N | X8: N | Y8: N
B9: 1 | D9: =Payroll_Raw!D7 -> 0 | E9: =Payroll_Raw!G48 -> 0 | F9: =Payroll_Raw!R7 -> 5305639.2 | G9: =Payroll_Raw!S7*8/100*12 -> 424451.14 | H9: =F9-G9 -> 4881188.1 | I9: =(20%*H9)+200000 -> 1176237.6 | J9: =SUM(I9:I9) -> 1176237.6 | K9: =H9-J9 -> 3704950.5 | L9: 0.07 | M9: =IF(K9-300000>0,'Tax Table - DONT ALTER'!D46,K9)*L9 -> 21000 | N9: 0.11 | O9: =IF(K9-600000>0,'Tax Table - DONT ALTER'!F46,K9-300000)*N9 -> 33000 | P9: 0.15 | Q9: =IF(K9-1100000>0,'Tax Table - DONT ALTER'!H47,K9-600000)*P9 -> 75000 | R9: 0.19 | S9: =IF(K9-1600000>0,'Tax Table - DONT ALTER'!J46,K9-1100000)*R9 -> 95000 | T9: 0.21 | U9: =IF(K9-3200000>0,'Tax Table - DONT ALTER'!L46,K9-1600000)*T9 -> 336000 | V9: 0.24 | W9: =IF(K9-3200000>0,K9-3200000)*V9 -> 121188.11 | X9: =1%*F9 -> 53056.392 | Y9: =IF(M9>=0,M9)+IF(O9>=0,O9)+IF(Q9>=0,Q9)+IF(S9>=0,S9)+IF(U9>=0,U9)+IF(W9>=0,W9) -> 681188.11 | Z9: =F9-G9-Y9 -> 4200000 | AA9: =Z9/12 -> 350000 | AB9: =Y9 -> 681188.11 | AC9: =AB9/12 -> 56765.676 | AD9: =G9 -> 424451.14 | AE9: =AD9/12 -> 35370.928 | AF9: =SUM(Payroll_Raw!I7:K7)*10% -> 530563.92 | AG9: =AF9/12 -> 44213.66 | AH9: =AD9+AF9 -> 955015.06 | AI9: =AE9+AG9 -> 79584.588
B10: =+B9+1 -> 2 | D10: =Payroll_Raw!D8 -> 0 | E10: =Payroll_Raw!G49 -> 0 | F10: =117856.55*12 -> 1414278.6 | G10: =F10*8/100 -> 113142.29 | H10: =F10-G10 -> 1301136.3 | I10: =(20%*H10)+200000 -> 460227.26 | J10: =SUM(I10:I10) -> 460227.26 | K10: =H10-J10 -> 840909.05 | L10: =L9 -> 0.07 | M10: =IF(K10-300000>0,'Tax Table - DONT ALTER'!D47,K10)*L10 -> 21000 | N10: =N9 -> 0.11 | O10: =IF(K10-600000>0,'Tax Table - DONT ALTER'!F47,K10-300000)*N10 -> 33000 | P10: =P9 -> 0.15 | Q10: =IF(K10-1100000>0,'Tax Table - DONT ALTER'!H48,K10-600000)*P10 -> 36136.357 | R10: =R9 -> 0.19 | S10: =IF(K10-1600000>0,'Tax Table - DONT ALTER'!J47,K10-1100000)*R10 -> -49227.281 | T10: =T9 -> 0.21 | U10: =IF(K10-3200000>0,'Tax Table - DONT ALTER'!L47,K10-1600000)*T10 -> -159409.1 | V10: =V9 -> 0.24 | W10: =IF(K10-3200000>0,K10-3200000)*V10 -> 0 | X10: =1%*F10 -> 14142.786 | Y10: =IF(M10>=0,M10)+IF(O10>=0,O10)+IF(Q10>=0,Q10)+IF(S10>=0,S10)+IF(U10>=0,U10)+IF(W10>=0,W10) -> 90136.357 | Z10: =F10-G10-Y10 -> 1211000 | AA10: =Z10/12 -> 100916.66 | AB10: =Y10 -> 90136.357 | AC10: =AB10/12 -> 7511.3631 | AD10: =G10 -> 113142.29 | AE10: =AD10/12 -> 9428.524 | AF10: =F10*10% -> 141427.86 | AG10: =AF10/12 -> 11785.655 | AH10: =AD10+AF10 -> 254570.15 | AI10: =AE10+AG10 -> 21214.179
B11: =+B10+1 -> 3 | D11: =Payroll_Raw!D9 -> 0 | E11: =Payroll_Raw!G50 -> 0 | F11: =Payroll_Raw!R9 -> 2934260 | G11: =Payroll_Raw!S9*8/100*12 -> 234740.8 | H11: =F11-G11 -> 2699519.2 | I11: =(20%*H11)+200000 -> 739903.85 | J11: =SUM(I11:I11) -> 739903.85 | K11: =H11-J11 -> 1959615.4 | L11: =L10 -> 0.07 | M11: =IF(K11-300000>0,'Tax Table - DONT ALTER'!D48,K11)*L11 -> 21000 | N11: =N10 -> 0.11 | O11: =IF(K11-600000>0,'Tax Table - DONT ALTER'!F48,K11-300000)*N11 -> 33000 | P11: =P10 -> 0.15 | Q11: =IF(K11-1100000>0,'Tax Table - DONT ALTER'!H49,K11-600000)*P11 -> 75000 | R11: =R10 -> 0.19 | S11: =IF(K11-1600000>0,'Tax Table - DONT ALTER'!J48,K11-1100000)*R11 -> 95000 | T11: =T10 -> 0.21 | U11: =IF(K11-3200000>0,'Tax Table - DONT ALTER'!L48,K11-1600000)*T11 -> 75519.232 | V11: =V10 -> 0.24 | W11: =IF(K11-3200000>0,K11-3200000)*V11 -> 0 | X11: =1%*F11 -> 29342.6 | Y11: =IF(M11>=0,M11)+IF(O11>=0,O11)+IF(Q11>=0,Q11)+IF(S11>=0,S11)+IF(U11>=0,U11)+IF(W11>=0,W11) -> 299519.23 | Z11: =F11-G11-Y11 -> 2400000 | AA11: =Z11/12 -> 200000 | AB11: =Y11 -> 299519.23 | AC11: =AB11/12 -> 24959.936 | AD11: =G11 -> 234740.8 | AE11: =AD11/12 -> 19561.734 | AF11: =SUM(Payroll_Raw!I9:K9)*10% -> 0 | AG11: =AF11/12 -> 0 | AH11: =AD11+AF11 -> 234740.8 | AI11: =AE11+AG11 -> 19561.734
B12: =+B11+1 -> 4 | D12: =Payroll_Raw!D10 -> 0 | E12: =Payroll_Raw!G51 -> 0 | F12: =Payroll_Raw!R10 -> 0 | G12: =SUM(Payroll_Raw!K10:S10)*8/100 -> 0 | H12: =F12-G12 -> 0 | I12: =(20%*H12)+200000 -> 200000 | J12: =SUM(I12:I12) -> 200000 | K12: =H12-J12 -> -200000 | L12: =L11 -> 0.07 | M12: =IF(K12-300000>0,'Tax Table - DONT ALTER'!D49,K12)*L12 -> -14000 | N12: =N11 -> 0.11 | O12: =IF(K12-600000>0,'Tax Table - DONT ALTER'!F49,K12-300000)*N12 -> -55000 | P12: =P11 -> 0.15 | Q12: =IF(K12-1100000>0,'Tax Table - DONT ALTER'!H50,K12-600000)*P12 -> -120000 | R12: =R11 -> 0.19 | S12: =IF(K12-1600000>0,'Tax Table - DONT ALTER'!J49,K12-1100000)*R12 -> -247000 | T12: =T11 -> 0.21 | U12: =IF(K12-3200000>0,'Tax Table - DONT ALTER'!L49,K12-1600000)*T12 -> -378000 | V12: =V11 -> 0.24 | W12: =IF(K12-3200000>0,K12-3200000)*V12 -> 0 | X12: =1%*F12 -> 0 | Y12: =IF(M12>=0,M12)+IF(O12>=0,O12)+IF(Q12>=0,Q12)+IF(S12>=0,S12)+IF(U12>=0,U12)+IF(W12>=0,W12) -> 0 | Z12: =F12-G12-Y12 -> 0 | AA12: =Z12/12 -> 0 | AB12: =Y12 -> 0 | AC12: =AB12/12 -> 0 | AD12: =G12 -> 0 | AE12: =AD12/12 -> 0 | AF12: =SUM(Payroll_Raw!I10:K10)*10% -> 0 | AG12: =AF12/12 -> 0 | AH12: =AD12+AF12 -> 0 | AI12: =AE12+AG12 -> 0
B13: =+B12+1 -> 5 | D13: =Payroll_Raw!D11 -> 0 | E13: =Payroll_Raw!G52 -> 0 | G13: =F13*8/100 -> 0 | H13: =F13-G13 -> 0 | I13: =(20%*H13)+200000 -> 200000 | J13: =SUM(I13:I13) -> 200000 | K13: =H13-J13 -> -200000 | L13: =L12 -> 0.07 | M13: =IF(K13-300000>0,'Tax Table - DONT ALTER'!D50,K13)*L13 -> -14000 | N13: =N12 -> 0.11 | O13: =IF(K13-600000>0,'Tax Table - DONT ALTER'!F50,K13-300000)*N13 -> -55000 | P13: =P12 -> 0.15 | Q13: =IF(K13-1100000>0,'Tax Table - DONT ALTER'!H51,K13-600000)*P13 -> -120000 | R13: =R12 -> 0.19 | S13: =IF(K13-1600000>0,'Tax Table - DONT ALTER'!J50,K13-1100000)*R13 -> -247000 | T13: =T12 -> 0.21 | U13: =IF(K13-3200000>0,'Tax Table - DONT ALTER'!L50,K13-1600000)*T13 -> -378000 | V13: =V12 -> 0.24 | W13: =IF(K13-3200000>0,K13-3200000)*V13 -> 0 | X13: =1%*F13 -> 0 | Y13: =IF(M13>=0,M13)+IF(O13>=0,O13)+IF(Q13>=0,Q13)+IF(S13>=0,S13)+IF(U13>=0,U13)+IF(W13>=0,W13) -> 0 | Z13: =F13-G13-Y13 -> 0 | AA13: =Z13/12 -> 0 | AB13: =Y13 -> 0 | AC13: =AB13/12 -> 0 | AD13: =G13 -> 0 | AE13: =AD13/12 -> 0 | AF13: =F13*10% -> 0 | AG13: =AF13/12 -> 0 | AH13: =AD13+AF13 -> 0 | AI13: =AE13+AG13 -> 0
B14: =+B13+1 -> 6 | D14: =Payroll_Raw!D12 -> 0 | E14: =Payroll_Raw!G53 -> 0 | G14: =F14*8/100 -> 0 | H14: =F14-G14 -> 0 | I14: =(20%*H14)+200000 -> 200000 | J14: =SUM(I14:I14) -> 200000 | K14: =H14-J14 -> -200000 | L14: =L13 -> 0.07 | M14: =IF(K14-300000>0,'Tax Table - DONT ALTER'!D51,K14)*L14 -> -14000 | N14: =N13 -> 0.11 | O14: =IF(K14-600000>0,'Tax Table - DONT ALTER'!F51,K14-300000)*N14 -> -55000 | P14: =P13 -> 0.15 | Q14: =IF(K14-1100000>0,'Tax Table - DONT ALTER'!H52,K14-600000)*P14 -> -120000 | R14: =R13 -> 0.19 | S14: =IF(K14-1600000>0,'Tax Table - DONT ALTER'!J51,K14-1100000)*R14 -> -247000 | T14: =T13 -> 0.21 | U14: =IF(K14-3200000>0,'Tax Table - DONT ALTER'!L51,K14-1600000)*T14 -> -378000 | V14: =V13 -> 0.24 | W14: =IF(K14-3200000>0,K14-3200000)*V14 -> 0 | X14: =1%*F14 -> 0 | Y14: =IF(M14>=0,M14)+IF(O14>=0,O14)+IF(Q14>=0,Q14)+IF(S14>=0,S14)+IF(U14>=0,U14)+IF(W14>=0,W14) -> 0 | Z14: =F14-G14-H14-Y14 -> 0 | AA14: =Z14/12 -> 0 | AB14: =Y14 -> 0 | AC14: =AB14/12 -> 0 | AD14: =G14 -> 0 | AE14: =AD14/12 -> 0 | AF14: =F14*10% -> 0 | AG14: =AF14/12 -> 0 | AH14: =AD14+AF14 -> 0 | AI14: =AE14+AG14 -> 0
B15: =+B14+1 -> 7 | D15: =Payroll_Raw!D13 -> 0 | E15: =Payroll_Raw!G54 -> 0 | G15: =F15*8/100 -> 0 | H15: =F15-G15 -> 0 | I15: =(20%*H15)+200000 -> 200000 | J15: =SUM(I15:I15) -> 200000 | K15: =H15-J15 -> -200000 | L15: =L14 -> 0.07 | M15: =IF(K15-300000>0,'Tax Table - DONT ALTER'!D52,K15)*L15 -> -14000 | N15: =N14 -> 0.11 | O15: =IF(K15-600000>0,'Tax Table - DONT ALTER'!F52,K15-300000)*N15 -> -55000 | P15: =P14 -> 0.15 | Q15: =IF(K15-1100000>0,'Tax Table - DONT ALTER'!H53,K15-600000)*P15 -> -120000 | R15: =R14 -> 0.19 | S15: =IF(K15-1600000>0,'Tax Table - DONT ALTER'!J52,K15-1100000)*R15 -> -247000 | T15: =T14 -> 0.21 | U15: =IF(K15-3200000>0,'Tax Table - DONT ALTER'!L52,K15-1600000)*T15 -> -378000 | V15: =V14 -> 0.24 | W15: =IF(K15-3200000>0,K15-3200000)*V15 -> 0 | X15: =1%*F15 -> 0 | Y15: =IF(M15>=0,M15)+IF(O15>=0,O15)+IF(Q15>=0,Q15)+IF(S15>=0,S15)+IF(U15>=0,U15)+IF(W15>=0,W15) -> 0 | Z15: =F15-G15-H15-Y15 -> 0 | AA15: =Z15/12 -> 0 | AB15: =Y15 -> 0 | AC15: =AB15/12 -> 0 | AD15: =G15 -> 0 | AE15: =AD15/12 -> 0 | AF15: =F15*10% -> 0 | AG15: =AF15/12 -> 0 | AH15: =AD15+AF15 -> 0 | AI15: =AE15+AG15 -> 0
B16: =+B15+1 -> 8 | D16: =Payroll_Raw!D14 -> 0 | E16: =Payroll_Raw!G55 -> 0 | G16: =F16*8/100 -> 0 | H16: =F16-G16 -> 0 | I16: =(20%*H16)+200000 -> 200000 | J16: =SUM(I16:I16) -> 200000 | K16: =H16-J16 -> -200000 | L16: =L15 -> 0.07 | M16: =IF(K16-300000>0,'Tax Table - DONT ALTER'!D53,K16)*L16 -> -14000 | N16: =N15 -> 0.11 | O16: =IF(K16-600000>0,'Tax Table - DONT ALTER'!F53,K16-300000)*N16 -> -55000 | P16: =P15 -> 0.15 | Q16: =IF(K16-1100000>0,'Tax Table - DONT ALTER'!H54,K16-600000)*P16 -> -120000 | R16: =R15 -> 0.19 | S16: =IF(K16-1600000>0,'Tax Table - DONT ALTER'!J53,K16-1100000)*R16 -> -247000 | T16: =T15 -> 0.21 | U16: =IF(K16-3200000>0,'Tax Table - DONT ALTER'!L53,K16-1600000)*T16 -> -378000 | V16: =V15 -> 0.24 | W16: =IF(K16-3200000>0,K16-3200000)*V16 -> 0 | X16: =1%*F16 -> 0 | Y16: =IF(M16>=0,M16)+IF(O16>=0,O16)+IF(Q16>=0,Q16)+IF(S16>=0,S16)+IF(U16>=0,U16)+IF(W16>=0,W16) -> 0 | Z16: =F16-G16-H16-Y16 -> 0 | AA16: =Z16/12 -> 0 | AB16: =Y16 -> 0 | AC16: =AB16/12 -> 0 | AD16: =G16 -> 0 | AE16: =AD16/12 -> 0 | AF16: =F16*10% -> 0 | AG16: =AF16/12 -> 0 | AH16: =AD16+AF16 -> 0 | AI16: =AE16+AG16 -> 0
B17: =+B16+1 -> 9 | D17: =Payroll_Raw!D15 -> 0 | E17: =Payroll_Raw!G56 -> 0 | G17: =F17*8/100 -> 0 | H17: =F17-G17 -> 0 | I17: =(20%*H17)+200000 -> 200000 | J17: =SUM(I17:I17) -> 200000 | K17: =H17-J17 -> -200000 | L17: =L16 -> 0.07 | M17: =IF(K17-300000>0,'Tax Table - DONT ALTER'!D54,K17)*L17 -> -14000 | N17: =N16 -> 0.11 | O17: =IF(K17-600000>0,'Tax Table - DONT ALTER'!F54,K17-300000)*N17 -> -55000 | P17: =P16 -> 0.15 | Q17: =IF(K17-1100000>0,'Tax Table - DONT ALTER'!H55,K17-600000)*P17 -> -120000 | R17: =R16 -> 0.19 | S17: =IF(K17-1600000>0,'Tax Table - DONT ALTER'!J54,K17-1100000)*R17 -> -247000 | T17: =T16 -> 0.21 | U17: =IF(K17-3200000>0,'Tax Table - DONT ALTER'!L54,K17-1600000)*T17 -> -378000 | V17: =V16 -> 0.24 | W17: =IF(K17-3200000>0,K17-3200000)*V17 -> 0 | X17: =1%*F17 -> 0 | Y17: =IF(M17>=0,M17)+IF(O17>=0,O17)+IF(Q17>=0,Q17)+IF(S17>=0,S17)+IF(U17>=0,U17)+IF(W17>=0,W17) -> 0 | Z17: =F17-G17-H17-Y17 -> 0 | AA17: =Z17/12 -> 0 | AB17: =Y17 -> 0 | AC17: =AB17/12 -> 0 | AD17: =G17 -> 0 | AE17: =AD17/12 -> 0 | AF17: =F17*10% -> 0 | AG17: =AF17/12 -> 0 | AH17: =AD17+AF17 -> 0 | AI17: =AE17+AG17 -> 0
B18: =+B17+1 -> 10 | D18: =Payroll_Raw!D16 -> 0 | E18: =Payroll_Raw!G57 -> 0 | G18: =F18*8/100 -> 0 | H18: =F18-G18 -> 0 | I18: =(20%*H18)+200000 -> 200000 | J18: =SUM(I18:I18) -> 200000 | K18: =H18-J18 -> -200000 | L18: =L17 -> 0.07 | M18: =IF(K18-300000>0,'Tax Table - DONT ALTER'!D55,K18)*L18 -> -14000 | N18: =N17 -> 0.11 | O18: =IF(K18-600000>0,'Tax Table - DONT ALTER'!F55,K18-300000)*N18 -> -55000 | P18: =P17 -> 0.15 | Q18: =IF(K18-1100000>0,'Tax Table - DONT ALTER'!H56,K18-600000)*P18 -> -120000 | R18: =R17 -> 0.19 | S18: =IF(K18-1600000>0,'Tax Table - DONT ALTER'!J55,K18-1100000)*R18 -> -247000 | T18: =T17 -> 0.21 | U18: =IF(K18-3200000>0,'Tax Table - DONT ALTER'!L55,K18-1600000)*T18 -> -378000 | V18: =V17 -> 0.24 | W18: =IF(K18-3200000>0,K18-3200000)*V18 -> 0 | X18: =1%*F18 -> 0 | Y18: =IF(M18>=0,M18)+IF(O18>=0,O18)+IF(Q18>=0,Q18)+IF(S18>=0,S18)+IF(U18>=0,U18)+IF(W18>=0,W18) -> 0 | Z18: =F18-G18-H18-Y18 -> 0 | AA18: =Z18/12 -> 0 | AB18: =Y18 -> 0 | AC18: =AB18/12 -> 0 | AD18: =G18 -> 0 | AE18: =AD18/12 -> 0 | AF18: =F18*10% -> 0 | AG18: =AF18/12 -> 0 | AH18: =AD18+AF18 -> 0 | AI18: =AE18+AG18 -> 0
B19: =+B18+1 -> 11 | D19: =Payroll_Raw!D17 -> 0 | E19: =Payroll_Raw!G58 -> 0 | G19: =F19*8/100 -> 0 | H19: =F19-G19 -> 0 | I19: =(20%*H19)+200000 -> 200000 | J19: =SUM(I19:I19) -> 200000 | K19: =H19-J19 -> -200000 | L19: =L18 -> 0.07 | M19: =IF(K19-300000>0,'Tax Table - DONT ALTER'!D56,K19)*L19 -> -14000 | N19: =N18 -> 0.11 | O19: =IF(K19-600000>0,'Tax Table - DONT ALTER'!F56,K19-300000)*N19 -> -55000 | P19: =P18 -> 0.15 | Q19: =IF(K19-1100000>0,'Tax Table - DONT ALTER'!H57,K19-600000)*P19 -> -120000 | R19: =R18 -> 0.19 | S19: =IF(K19-1600000>0,'Tax Table - DONT ALTER'!J56,K19-1100000)*R19 -> -247000 | T19: =T18 -> 0.21 | U19: =IF(K19-3200000>0,'Tax Table - DONT ALTER'!L56,K19-1600000)*T19 -> -378000 | V19: =V18 -> 0.24 | W19: =IF(K19-3200000>0,K19-3200000)*V19 -> 0 | X19: =1%*F19 -> 0 | Y19: =IF(M19>=0,M19)+IF(O19>=0,O19)+IF(Q19>=0,Q19)+IF(S19>=0,S19)+IF(U19>=0,U19)+IF(W19>=0,W19) -> 0 | Z19: =F19-G19-H19-Y19 -> 0 | AA19: =Z19/12 -> 0 | AB19: =Y19 -> 0 | AC19: =AB19/12 -> 0 | AD19: =G19 -> 0 | AE19: =AD19/12 -> 0 | AF19: =F19*10% -> 0 | AG19: =AF19/12 -> 0 | AH19: =AD19+AF19 -> 0 | AI19: =AE19+AG19 -> 0
B20: =+B19+1 -> 12 | D20: =Payroll_Raw!D18 -> 0 | E20: =Payroll_Raw!G59 -> 0 | G20: =F20*8/100 -> 0 | H20: =F20-G20 -> 0 | I20: =(20%*H20)+200000 -> 200000 | J20: =SUM(I20:I20) -> 200000 | K20: =H20-J20 -> -200000 | L20: =L19 -> 0.07 | M20: =IF(K20-300000>0,'Tax Table - DONT ALTER'!D57,K20)*L20 -> -14000 | N20: =N19 -> 0.11 | O20: =IF(K20-600000>0,'Tax Table - DONT ALTER'!F57,K20-300000)*N20 -> -55000 | P20: =P19 -> 0.15 | Q20: =IF(K20-1100000>0,'Tax Table - DONT ALTER'!H58,K20-600000)*P20 -> -120000 | R20: =R19 -> 0.19 | S20: =IF(K20-1600000>0,'Tax Table - DONT ALTER'!J57,K20-1100000)*R20 -> -247000 | T20: =T19 -> 0.21 | U20: =IF(K20-3200000>0,'Tax Table - DONT ALTER'!L57,K20-1600000)*T20 -> -378000 | V20: =V19 -> 0.24 | W20: =IF(K20-3200000>0,K20-3200000)*V20 -> 0 | X20: =1%*F20 -> 0 | Y20: =IF(M20>=0,M20)+IF(O20>=0,O20)+IF(Q20>=0,Q20)+IF(S20>=0,S20)+IF(U20>=0,U20)+IF(W20>=0,W20) -> 0 | Z20: =F20-G20-H20-Y20 -> 0 | AA20: =Z20/12 -> 0 | AB20: =Y20 -> 0 | AC20: =AB20/12 -> 0 | AD20: =G20 -> 0 | AE20: =AD20/12 -> 0 | AF20: =F20*10% -> 0 | AG20: =AF20/12 -> 0 | AH20: =AD20+AF20 -> 0 | AI20: =AE20+AG20 -> 0
B21: =+B20+1 -> 13 | D21: =Payroll_Raw!D19 -> 0 | E21: =Payroll_Raw!G60 -> 0 | G21: =F21*8/100 -> 0 | H21: =F21-G21 -> 0 | I21: =(20%*H21)+200000 -> 200000 | J21: =SUM(I21:I21) -> 200000 | K21: =H21-J21 -> -200000 | L21: =L20 -> 0.07 | M21: =IF(K21-300000>0,'Tax Table - DONT ALTER'!D58,K21)*L21 -> -14000 | N21: =N20 -> 0.11 | O21: =IF(K21-600000>0,'Tax Table - DONT ALTER'!F58,K21-300000)*N21 -> -55000 | P21: =P20 -> 0.15 | Q21: =IF(K21-1100000>0,'Tax Table - DONT ALTER'!H59,K21-600000)*P21 -> -120000 | R21: =R20 -> 0.19 | S21: =IF(K21-1600000>0,'Tax Table - DONT ALTER'!J58,K21-1100000)*R21 -> -247000 | T21: =T20 -> 0.21 | U21: =IF(K21-3200000>0,'Tax Table - DONT ALTER'!L58,K21-1600000)*T21 -> -378000 | V21: =V20 -> 0.24 | W21: =IF(K21-3200000>0,K21-3200000)*V21 -> 0 | X21: =1%*F21 -> 0 | Y21: =IF(M21>=0,M21)+IF(O21>=0,O21)+IF(Q21>=0,Q21)+IF(S21>=0,S21)+IF(U21>=0,U21)+IF(W21>=0,W21) -> 0 | Z21: =F21-G21-H21-Y21 -> 0 | AA21: =Z21/12 -> 0 | AB21: =Y21 -> 0 | AC21: =AB21/12 -> 0 | AD21: =G21 -> 0 | AE21: =AD21/12 -> 0 | AF21: =F21*10% -> 0 | AG21: =AF21/12 -> 0 | AH21: =AD21+AF21 -> 0 | AI21: =AE21+AG21 -> 0
B22: =+B21+1 -> 14 | D22: =Payroll_Raw!D20 -> 0 | E22: =Payroll_Raw!G61 -> 0 | G22: =F22*8/100 -> 0 | H22: =F22-G22 -> 0 | I22: =(20%*H22)+200000 -> 200000 | J22: =SUM(I22:I22) -> 200000 | K22: =H22-J22 -> -200000 | L22: =L21 -> 0.07 | M22: =IF(K22-300000>0,'Tax Table - DONT ALTER'!D59,K22)*L22 -> -14000 | N22: =N21 -> 0.11 | O22: =IF(K22-600000>0,'Tax Table - DONT ALTER'!F59,K22-300000)*N22 -> -55000 | P22: =P21 -> 0.15 | Q22: =IF(K22-1100000>0,'Tax Table - DONT ALTER'!H60,K22-600000)*P22 -> -120000 | R22: =R21 -> 0.19 | S22: =IF(K22-1600000>0,'Tax Table - DONT ALTER'!J59,K22-1100000)*R22 -> -247000 | T22: =T21 -> 0.21 | U22: =IF(K22-3200000>0,'Tax Table - DONT ALTER'!L59,K22-1600000)*T22 -> -378000 | V22: =V21 -> 0.24 | W22: =IF(K22-3200000>0,K22-3200000)*V22 -> 0 | X22: =1%*F22 -> 0 | Y22: =IF(M22>=0,M22)+IF(O22>=0,O22)+IF(Q22>=0,Q22)+IF(S22>=0,S22)+IF(U22>=0,U22)+IF(W22>=0,W22) -> 0 | Z22: =F22-G22-H22-Y22 -> 0 | AA22: =Z22/12 -> 0 | AB22: =Y22 -> 0 | AC22: =AB22/12 -> 0 | AD22: =G22 -> 0 | AE22: =AD22/12 -> 0 | AF22: =F22*10% -> 0 | AG22: =AF22/12 -> 0 | AH22: =AD22+AF22 -> 0 | AI22: =AE22+AG22 -> 0
B23: =+B22+1 -> 15 | D23: =Payroll_Raw!D21 -> 0 | E23: =Payroll_Raw!G62 -> 0 | G23: =F23*8/100 -> 0 | H23: =F23-G23 -> 0 | I23: =(20%*H23)+200000 -> 200000 | J23: =SUM(I23:I23) -> 200000 | K23: =H23-J23 -> -200000 | L23: =L22 -> 0.07 | M23: =IF(K23-300000>0,'Tax Table - DONT ALTER'!D60,K23)*L23 -> -14000 | N23: =N22 -> 0.11 | O23: =IF(K23-600000>0,'Tax Table - DONT ALTER'!F60,K23-300000)*N23 -> -55000 | P23: =P22 -> 0.15 | Q23: =IF(K23-1100000>0,'Tax Table - DONT ALTER'!H61,K23-600000)*P23 -> -120000 | R23: =R22 -> 0.19 | S23: =IF(K23-1600000>0,'Tax Table - DONT ALTER'!J60,K23-1100000)*R23 -> -247000 | T23: =T22 -> 0.21 | U23: =IF(K23-3200000>0,'Tax Table - DONT ALTER'!L60,K23-1600000)*T23 -> -378000 | V23: =V22 -> 0.24 | W23: =IF(K23-3200000>0,K23-3200000)*V23 -> 0 | X23: =1%*F23 -> 0 | Y23: =IF(M23>=0,M23)+IF(O23>=0,O23)+IF(Q23>=0,Q23)+IF(S23>=0,S23)+IF(U23>=0,U23)+IF(W23>=0,W23) -> 0 | Z23: =F23-G23-H23-Y23 -> 0 | AA23: =Z23/12 -> 0 | AB23: =Y23 -> 0 | AC23: =AB23/12 -> 0 | AD23: =G23 -> 0 | AE23: =AD23/12 -> 0 | AF23: =F23*10% -> 0 | AG23: =AF23/12 -> 0 | AH23: =AD23+AF23 -> 0 | AI23: =AE23+AG23 -> 0
B24: =+B23+1 -> 16 | D24: =Payroll_Raw!D22 -> 0 | E24: =Payroll_Raw!G63 -> 0 | G24: =F24*8/100 -> 0 | H24: =F24-G24 -> 0 | I24: =(20%*H24)+200000 -> 200000 | J24: =SUM(I24:I24) -> 200000 | K24: =H24-J24 -> -200000 | L24: =L22 -> 0.07 | M24: =IF(K24-300000>0,'Tax Table - DONT ALTER'!D60,K24)*L24 -> -14000 | N24: =N22 -> 0.11 | O24: =IF(K24-600000>0,'Tax Table - DONT ALTER'!F60,K24-300000)*N24 -> -55000 | P24: =P22 -> 0.15 | Q24: =IF(K24-1100000>0,'Tax Table - DONT ALTER'!H61,K24-600000)*P24 -> -120000 | R24: =R22 -> 0.19 | S24: =IF(K24-1600000>0,'Tax Table - DONT ALTER'!J60,K24-1100000)*R24 -> -247000 | T24: =T22 -> 0.21 | U24: =IF(K24-3200000>0,'Tax Table - DONT ALTER'!L60,K24-1600000)*T24 -> -378000 | V24: =V22 -> 0.24 | W24: =IF(K24-3200000>0,K24-3200000)*V24 -> 0 | X24: =1%*F24 -> 0 | Y24: =IF(M24>=0,M24)+IF(O24>=0,O24)+IF(Q24>=0,Q24)+IF(S24>=0,S24)+IF(U24>=0,U24)+IF(W24>=0,W24) -> 0 | Z24: =F24-G24-H24-Y24 -> 0 | AA24: =Z24/12 -> 0 | AB24: =Y24 -> 0 | AC24: =AB24/12 -> 0 | AD24: =G24 -> 0 | AE24: =AD24/12 -> 0 | AF24: =F24*10% -> 0 | AG24: =AF24/12 -> 0 | AH24: =AD24+AF24 -> 0 | AI24: =AE24+AG24 -> 0
B25: =+B24+1 -> 17 | D25: =Payroll_Raw!D23 -> 0 | E25: =Payroll_Raw!G64 -> 0 | G25: =F25*8/100 -> 0 | H25: =F25-G25 -> 0 | I25: =(20%*H25)+200000 -> 200000 | J25: =SUM(I25:I25) -> 200000 | K25: =H25-J25 -> -200000 | L25: =L24 -> 0.07 | M25: =IF(K25-300000>0,'Tax Table - DONT ALTER'!D61,K25)*L25 -> -14000 | N25: =N24 -> 0.11 | O25: =IF(K25-600000>0,'Tax Table - DONT ALTER'!F61,K25-300000)*N25 -> -55000 | P25: =P24 -> 0.15 | Q25: =IF(K25-1100000>0,'Tax Table - DONT ALTER'!H62,K25-600000)*P25 -> -120000 | R25: =R24 -> 0.19 | S25: =IF(K25-1600000>0,'Tax Table - DONT ALTER'!J61,K25-1100000)*R25 -> -247000 | T25: =T24 -> 0.21 | U25: =IF(K25-3200000>0,'Tax Table - DONT ALTER'!L61,K25-1600000)*T25 -> -378000 | V25: =V24 -> 0.24 | W25: =IF(K25-3200000>0,K25-3200000)*V25 -> 0 | X25: =1%*F25 -> 0 | Y25: =IF(M25>=0,M25)+IF(O25>=0,O25)+IF(Q25>=0,Q25)+IF(S25>=0,S25)+IF(U25>=0,U25)+IF(W25>=0,W25) -> 0 | Z25: =F25-G25-H25-Y25 -> 0 | AA25: =Z25/12 -> 0 | AB25: =Y25 -> 0 | AC25: =AB25/12 -> 0 | AD25: =G25 -> 0 | AE25: =AD25/12 -> 0 | AF25: =F25*10% -> 0 | AG25: =AF25/12 -> 0 | AH25: =AD25+AF25 -> 0 | AI25: =AE25+AG25 -> 0
B26: =+B25+1 -> 18 | D26: =Payroll_Raw!D24 -> 0 | E26: =Payroll_Raw!G65 -> 0 | G26: =F26*8/100 -> 0 | H26: =F26-G26 -> 0 | I26: =(20%*H26)+200000 -> 200000 | J26: =SUM(I26:I26) -> 200000 | K26: =F26-J26 -> -200000 | L26: =L25 -> 0.07 | M26: =IF(K26-300000>0,'Tax Table - DONT ALTER'!D62,K26)*L26 -> -14000 | N26: =N25 -> 0.11 | O26: =IF(K26-600000>0,'Tax Table - DONT ALTER'!F62,K26-300000)*N26 -> -55000 | P26: =P25 -> 0.15 | Q26: =IF(K26-1100000>0,'Tax Table - DONT ALTER'!H63,K26-600000)*P26 -> -120000 | R26: =R25 -> 0.19 | S26: =IF(K26-1600000>0,'Tax Table - DONT ALTER'!J62,K26-1100000)*R26 -> -247000 | T26: =T25 -> 0.21 | U26: =IF(K26-3200000>0,'Tax Table - DONT ALTER'!L62,K26-1600000)*T26 -> -378000 | V26: =V25 -> 0.24 | W26: =IF(K26-3200000>0,K26-3200000)*V26 -> 0 | X26: =1%*F26 -> 0 | Y26: =IF(M26>=0,M26)+IF(O26>=0,O26)+IF(Q26>=0,Q26)+IF(S26>=0,S26)+IF(U26>=0,U26)+IF(W26>=0,W26) -> 0 | Z26: =F26-G26-H26-Y26 -> 0 | AA26: =Z26/12 -> 0 | AB26: =Y26 -> 0 | AC26: =AB26/12 -> 0 | AD26: =G26 -> 0 | AE26: =AD26/12 -> 0 | AF26: =F26*10% -> 0 | AG26: =AF26/12 -> 0 | AH26: =AD26+AF26 -> 0 | AI26: =AE26+AG26 -> 0
B27: =+B26+1 -> 19 | D27: =Payroll_Raw!D25 -> 0 | E27: =Payroll_Raw!G66 -> 0 | G27: =F27*8/100 -> 0 | H27: =F27-G27 -> 0 | I27: =(20%*H27)+200000 -> 200000 | J27: =SUM(I27:I27) -> 200000 | K27: =F27-J27 -> -200000 | L27: =L26 -> 0.07 | M27: =IF(K27-300000>0,'Tax Table - DONT ALTER'!D63,K27)*L27 -> -14000 | N27: =N26 -> 0.11 | O27: =IF(K27-600000>0,'Tax Table - DONT ALTER'!F63,K27-300000)*N27 -> -55000 | P27: =P26 -> 0.15 | Q27: =IF(K27-1100000>0,'Tax Table - DONT ALTER'!H64,K27-600000)*P27 -> -120000 | R27: =R26 -> 0.19 | S27: =IF(K27-1600000>0,'Tax Table - DONT ALTER'!J63,K27-1100000)*R27 -> -247000 | T27: =T26 -> 0.21 | U27: =IF(K27-3200000>0,'Tax Table - DONT ALTER'!L63,K27-1600000)*T27 -> -378000 | V27: =V26 -> 0.24 | W27: =IF(K27-3200000>0,K27-3200000)*V27 -> 0 | X27: =1%*F27 -> 0 | Y27: =IF(M27>=0,M27)+IF(O27>=0,O27)+IF(Q27>=0,Q27)+IF(S27>=0,S27)+IF(U27>=0,U27)+IF(W27>=0,W27) -> 0 | Z27: =F27-G27-H27-Y27 -> 0 | AA27: =Z27/12 -> 0 | AB27: =Y27 -> 0 | AC27: =AB27/12 -> 0 | AD27: =G27 -> 0 | AE27: =AD27/12 -> 0 | AF27: =F27*10% -> 0 | AG27: =AF27/12 -> 0 | AH27: =AD27+AF27 -> 0 | AI27: =AE27+AG27 -> 0
B28: =+B27+1 -> 20 | D28: =Payroll_Raw!D26 -> 0 | E28: =Payroll_Raw!G67 -> 0 | G28: =F28*8/100 -> 0 | H28: =F28-G28 -> 0 | I28: =(20%*H28)+200000 -> 200000 | J28: =SUM(I28:I28) -> 200000 | K28: =F28-J28 -> -200000 | L28: =L27 -> 0.07 | M28: =IF(K28-300000>0,'Tax Table - DONT ALTER'!D64,K28)*L28 -> -14000 | N28: =N27 -> 0.11 | O28: =IF(K28-600000>0,'Tax Table - DONT ALTER'!F64,K28-300000)*N28 -> -55000 | P28: =P27 -> 0.15 | Q28: =IF(K28-1100000>0,'Tax Table - DONT ALTER'!H65,K28-600000)*P28 -> -120000 | R28: =R27 -> 0.19 | S28: =IF(K28-1600000>0,'Tax Table - DONT ALTER'!J64,K28-1100000)*R28 -> -247000 | T28: =T27 -> 0.21 | U28: =IF(K28-3200000>0,'Tax Table - DONT ALTER'!L64,K28-1600000)*T28 -> -378000 | V28: =V27 -> 0.24 | W28: =IF(K28-3200000>0,K28-3200000)*V28 -> 0 | X28: =1%*F28 -> 0 | Y28: =IF(M28>=0,M28)+IF(O28>=0,O28)+IF(Q28>=0,Q28)+IF(S28>=0,S28)+IF(U28>=0,U28)+IF(W28>=0,W28) -> 0 | Z28: =F28-G28-H28-Y28 -> 0 | AA28: =Z28/12 -> 0 | AB28: =Y28 -> 0 | AC28: =AB28/12 -> 0 | AD28: =G28 -> 0 | AE28: =AD28/12 -> 0 | AF28: =F28*10% -> 0 | AG28: =AF28/12 -> 0 | AH28: =AD28+AF28 -> 0 | AI28: =AE28+AG28 -> 0
B29: =+B28+1 -> 21 | D29: =Payroll_Raw!D27 -> 0 | E29: =Payroll_Raw!G68 -> 0 | G29: =F29*8/100 -> 0 | H29: =F29-G29 -> 0 | I29: =(20%*H29)+200000 -> 200000 | J29: =SUM(I29:I29) -> 200000 | K29: =F29-J29 -> -200000 | L29: =L28 -> 0.07 | M29: =IF(K29-300000>0,'Tax Table - DONT ALTER'!D65,K29)*L29 -> -14000 | N29: =N28 -> 0.11 | O29: =IF(K29-600000>0,'Tax Table - DONT ALTER'!F65,K29-300000)*N29 -> -55000 | P29: =P28 -> 0.15 | Q29: =IF(K29-1100000>0,'Tax Table - DONT ALTER'!H66,K29-600000)*P29 -> -120000 | R29: =R28 -> 0.19 | S29: =IF(K29-1600000>0,'Tax Table - DONT ALTER'!J65,K29-1100000)*R29 -> -247000 | T29: =T28 -> 0.21 | U29: =IF(K29-3200000>0,'Tax Table - DONT ALTER'!L65,K29-1600000)*T29 -> -378000 | V29: =V28 -> 0.24 | W29: =IF(K29-3200000>0,K29-3200000)*V29 -> 0 | X29: =1%*F29 -> 0 | Y29: =IF(M29>=0,M29)+IF(O29>=0,O29)+IF(Q29>=0,Q29)+IF(S29>=0,S29)+IF(U29>=0,U29)+IF(W29>=0,W29) -> 0 | Z29: =F29-G29-H29-Y29 -> 0 | AA29: =Z29/12 -> 0 | AB29: =Y29 -> 0 | AC29: =AB29/12 -> 0 | AD29: =G29 -> 0 | AE29: =AD29/12 -> 0 | AF29: =F29*10% -> 0 | AG29: =AF29/12 -> 0 | AH29: =AD29+AF29 -> 0 | AI29: =AE29+AG29 -> 0
B30: =+B29+1 -> 22 | D30: =Payroll_Raw!D28 -> 0 | E30: =Payroll_Raw!G69 -> 0 | G30: =F30*8/100 -> 0 | H30: =F30-G30 -> 0 | I30: =(20%*H30)+200000 -> 200000 | J30: =SUM(I30:I30) -> 200000 | K30: =F30-J30 -> -200000 | L30: =L29 -> 0.07 | M30: =IF(K30-300000>0,'Tax Table - DONT ALTER'!D66,K30)*L30 -> -14000 | N30: =N29 -> 0.11 | O30: =IF(K30-600000>0,'Tax Table - DONT ALTER'!F66,K30-300000)*N30 -> -55000 | P30: =P29 -> 0.15 | Q30: =IF(K30-1100000>0,'Tax Table - DONT ALTER'!H67,K30-600000)*P30 -> -120000 | R30: =R29 -> 0.19 | S30: =IF(K30-1600000>0,'Tax Table - DONT ALTER'!J66,K30-1100000)*R30 -> -247000 | T30: =T29 -> 0.21 | U30: =IF(K30-3200000>0,'Tax Table - DONT ALTER'!L66,K30-1600000)*T30 -> -378000 | V30: =V29 -> 0.24 | W30: =IF(K30-3200000>0,K30-3200000)*V30 -> 0 | X30: =1%*F30 -> 0 | Y30: =IF(M30>=0,M30)+IF(O30>=0,O30)+IF(Q30>=0,Q30)+IF(S30>=0,S30)+IF(U30>=0,U30)+IF(W30>=0,W30) -> 0 | Z30: =F30-G30-H30-Y30 -> 0 | AA30: =Z30/12 -> 0 | AB30: =Y30 -> 0 | AC30: =AB30/12 -> 0 | AD30: =G30 -> 0 | AE30: =AD30/12 -> 0 | AF30: =F30*10% -> 0 | AG30: =AF30/12 -> 0 | AH30: =AD30+AF30 -> 0 | AI30: =AE30+AG30 -> 0
B31: =+B30+1 -> 23 | D31: =Payroll_Raw!D29 -> 0 | E31: =Payroll_Raw!G70 -> 0 | G31: =F31*8/100 -> 0 | H31: =F31-G31 -> 0 | I31: =(20%*H31)+200000 -> 200000 | J31: =SUM(I31:I31) -> 200000 | K31: =F31-J31 -> -200000 | L31: =L30 -> 0.07 | M31: =IF(K31-300000>0,'Tax Table - DONT ALTER'!D67,K31)*L31 -> -14000 | N31: =N30 -> 0.11 | O31: =IF(K31-600000>0,'Tax Table - DONT ALTER'!F67,K31-300000)*N31 -> -55000 | P31: =P30 -> 0.15 | Q31: =IF(K31-1100000>0,'Tax Table - DONT ALTER'!H68,K31-600000)*P31 -> -120000 | R31: =R30 -> 0.19 | S31: =IF(K31-1600000>0,'Tax Table - DONT ALTER'!J67,K31-1100000)*R31 -> -247000 | T31: =T30 -> 0.21 | U31: =IF(K31-3200000>0,'Tax Table - DONT ALTER'!L67,K31-1600000)*T31 -> -378000 | V31: =V30 -> 0.24 | W31: =IF(K31-3200000>0,K31-3200000)*V31 -> 0 | X31: =1%*F31 -> 0 | Y31: =IF(M31>=0,M31)+IF(O31>=0,O31)+IF(Q31>=0,Q31)+IF(S31>=0,S31)+IF(U31>=0,U31)+IF(W31>=0,W31) -> 0 | Z31: =F31-G31-H31-Y31 -> 0 | AA31: =Z31/12 -> 0 | AB31: =Y31 -> 0 | AC31: =AB31/12 -> 0 | AD31: =G31 -> 0 | AE31: =AD31/12 -> 0 | AF31: =F31*10% -> 0 | AG31: =AF31/12 -> 0 | AH31: =AD31+AF31 -> 0 | AI31: =AE31+AG31 -> 0
B32: =+B31+1 -> 24 | D32: =Payroll_Raw!D30 -> 0 | E32: =Payroll_Raw!G71 -> 0 | G32: =F32*8/100 -> 0 | H32: =F32-G32 -> 0 | I32: =(20%*H32)+200000 -> 200000 | J32: =SUM(I32:I32) -> 200000 | K32: =F32-J32 -> -200000 | L32: =L31 -> 0.07 | M32: =IF(K32-300000>0,'Tax Table - DONT ALTER'!D68,K32)*L32 -> -14000 | N32: =N31 -> 0.11 | O32: =IF(K32-600000>0,'Tax Table - DONT ALTER'!F68,K32-300000)*N32 -> -55000 | P32: =P31 -> 0.15 | Q32: =IF(K32-1100000>0,'Tax Table - DONT ALTER'!H69,K32-600000)*P32 -> -120000 | R32: =R31 -> 0.19 | S32: =IF(K32-1600000>0,'Tax Table - DONT ALTER'!J68,K32-1100000)*R32 -> -247000 | T32: =T31 -> 0.21 | U32: =IF(K32-3200000>0,'Tax Table - DONT ALTER'!L68,K32-1600000)*T32 -> -378000 | V32: =V31 -> 0.24 | W32: =IF(K32-3200000>0,K32-3200000)*V32 -> 0 | X32: =1%*F32 -> 0 | Y32: =IF(M32>=0,M32)+IF(O32>=0,O32)+IF(Q32>=0,Q32)+IF(S32>=0,S32)+IF(U32>=0,U32)+IF(W32>=0,W32) -> 0 | Z32: =F32-G32-H32-Y32 -> 0 | AA32: =Z32/12 -> 0 | AC32: =AB32/12 -> 0 | AD32: =G32 -> 0 | AE32: =AD32/12 -> 0 | AF32: =F32*10% -> 0 | AG32: =AF32/12 -> 0 | AH32: =AD32+AF32 -> 0 | AI32: =AE32+AG32 -> 0
B33: =+B32+1 -> 25 | D33: =Payroll_Raw!D31 -> 0 | E33: =Payroll_Raw!G72 -> 0 | G33: =F33*8/100 -> 0 | H33: =F33-G33 -> 0 | I33: =(20%*H33)+200000 -> 200000 | J33: =SUM(I33:I33) -> 200000 | K33: =F33-J33 -> -200000 | L33: =L32 -> 0.07 | M33: =IF(K33-300000>0,'Tax Table - DONT ALTER'!D69,K33)*L33 -> -14000 | N33: =N32 -> 0.11 | O33: =IF(K33-600000>0,'Tax Table - DONT ALTER'!F69,K33-300000)*N33 -> -55000 | P33: =P32 -> 0.15 | Q33: =IF(K33-1100000>0,'Tax Table - DONT ALTER'!H70,K33-600000)*P33 -> -120000 | R33: =R32 -> 0.19 | S33: =IF(K33-1600000>0,'Tax Table - DONT ALTER'!J69,K33-1100000)*R33 -> -247000 | T33: =T32 -> 0.21 | U33: =IF(K33-3200000>0,'Tax Table - DONT ALTER'!L69,K33-1600000)*T33 -> -378000 | V33: =V32 -> 0.24 | W33: =IF(K33-3200000>0,K33-3200000)*V33 -> 0 | X33: =1%*F33 -> 0 | Y33: =IF(M33>=0,M33)+IF(O33>=0,O33)+IF(Q33>=0,Q33)+IF(S33>=0,S33)+IF(U33>=0,U33)+IF(W33>=0,W33) -> 0 | Z33: =F33-G33-H33-Y33 -> 0 | AA33: =Z33/12 -> 0 | AC33: =AB33/12 -> 0 | AD33: =G33 -> 0 | AE33: =AD33/12 -> 0 | AF33: =F33*10% -> 0 | AG33: =AF33/12 -> 0 | AH33: =AD33+AF33 -> 0 | AI33: =AE33+AG33 -> 0
B34: =+B33+1 -> 26 | D34: =Payroll_Raw!D32 -> 0 | E34: =Payroll_Raw!G73 -> 0 | G34: =F34*8/100 -> 0 | H34: =F34-G34 -> 0 | I34: =(20%*H34)+200000 -> 200000 | J34: =SUM(I34:I34) -> 200000 | K34: =F34-J34 -> -200000 | L34: =L33 -> 0.07 | M34: =IF(K34-300000>0,'Tax Table - DONT ALTER'!D70,K34)*L34 -> -14000 | N34: =N33 -> 0.11 | O34: =IF(K34-600000>0,'Tax Table - DONT ALTER'!F70,K34-300000)*N34 -> -55000 | P34: =P33 -> 0.15 | Q34: =IF(K34-1100000>0,'Tax Table - DONT ALTER'!H71,K34-600000)*P34 -> -120000 | R34: =R33 -> 0.19 | S34: =IF(K34-1600000>0,'Tax Table - DONT ALTER'!J70,K34-1100000)*R34 -> -247000 | T34: =T33 -> 0.21 | U34: =IF(K34-3200000>0,'Tax Table - DONT ALTER'!L70,K34-1600000)*T34 -> -378000 | V34: =V33 -> 0.24 | W34: =IF(K34-3200000>0,K34-3200000)*V34 -> 0 | X34: =1%*F34 -> 0 | Y34: =IF(M34>=0,M34)+IF(O34>=0,O34)+IF(Q34>=0,Q34)+IF(S34>=0,S34)+IF(U34>=0,U34)+IF(W34>=0,W34) -> 0 | Z34: =F34-G34-H34-Y34 -> 0 | AA34: =Z34/12 -> 0 | AC34: =AB34/12 -> 0 | AE34: =AD34/12 -> 0 | AF34: =F34*10% -> 0 | AG34: =AF34/12 -> 0 | AH34: =AD34+AF34 -> 0 | AI34: =AE34+AG34 -> 0
B35: =+B34+1 -> 27 | D35: =Payroll_Raw!D33 -> 0 | E35: =Payroll_Raw!G74 -> 0 | G35: =F35*8/100 -> 0 | H35: =F35-G35 -> 0 | I35: =(20%*H35)+200000 -> 200000 | J35: =SUM(I35:I35) -> 200000 | K35: =F35-J35 -> -200000 | L35: =L34 -> 0.07 | M35: =IF(K35-300000>0,'Tax Table - DONT ALTER'!D71,K35)*L35 -> -14000 | N35: =N34 -> 0.11 | O35: =IF(K35-600000>0,'Tax Table - DONT ALTER'!F71,K35-300000)*N35 -> -55000 | P35: =P34 -> 0.15 | Q35: =IF(K35-1100000>0,'Tax Table - DONT ALTER'!H72,K35-600000)*P35 -> -120000 | R35: =R34 -> 0.19 | S35: =IF(K35-1600000>0,'Tax Table - DONT ALTER'!J71,K35-1100000)*R35 -> -247000 | T35: =T34 -> 0.21 | U35: =IF(K35-3200000>0,'Tax Table - DONT ALTER'!L71,K35-1600000)*T35 -> -378000 | V35: =V34 -> 0.24 | W35: =IF(K35-3200000>0,K35-3200000)*V35 -> 0 | X35: =1%*F35 -> 0 | Y35: =IF(M35>=0,M35)+IF(O35>=0,O35)+IF(Q35>=0,Q35)+IF(S35>=0,S35)+IF(U35>=0,U35)+IF(W35>=0,W35) -> 0 | Z35: =F35-G35-H35-Y35 -> 0 | AA35: =Z35/12 -> 0 | AC35: =AB35/12 -> 0 | AE35: =AD35/12 -> 0 | AG35: =AF35/12 -> 0 | AH35: =AD35+AF35 -> 0 | AI35: =AE35+AG35 -> 0
B36: =+B35+1 -> 28 | D36: =Payroll_Raw!D34 -> 0 | E36: =Payroll_Raw!G75 -> 0 | G36: =F36*8/100 -> 0 | H36: =F36-G36 -> 0 | I36: =(20%*H36)+200000 -> 200000 | J36: =SUM(I36:I36) -> 200000 | K36: =F36-J36 -> -200000 | L36: =L35 -> 0.07 | M36: =IF(K36-300000>0,'Tax Table - DONT ALTER'!D72,K36)*L36 -> -14000 | N36: =N35 -> 0.11 | O36: =IF(K36-600000>0,'Tax Table - DONT ALTER'!F72,K36-300000)*N36 -> -55000 | P36: =P35 -> 0.15 | Q36: =IF(K36-1100000>0,'Tax Table - DONT ALTER'!H73,K36-600000)*P36 -> -120000 | R36: =R35 -> 0.19 | S36: =IF(K36-1600000>0,'Tax Table - DONT ALTER'!J72,K36-1100000)*R36 -> -247000 | T36: =T35 -> 0.21 | U36: =IF(K36-3200000>0,'Tax Table - DONT ALTER'!L72,K36-1600000)*T36 -> -378000 | V36: =V35 -> 0.24 | W36: =IF(K36-3200000>0,K36-3200000)*V36 -> 0 | X36: =1%*F36 -> 0 | Y36: =IF(M36>=0,M36)+IF(O36>=0,O36)+IF(Q36>=0,Q36)+IF(S36>=0,S36)+IF(U36>=0,U36)+IF(W36>=0,W36) -> 0 | Z36: =F36-G36-H36-Y36 -> 0 | AA36: =Z36/12 -> 0 | AC36: =AB36/12 -> 0 | AE36: =AD36/12 -> 0 | AG36: =AF36/12 -> 0 | AH36: =AD36+AF36 -> 0 | AI36: =AE36+AG36 -> 0
B37: =+B36+1 -> 29 | D37: =Payroll_Raw!D35 -> 0 | E37: =Payroll_Raw!G76 -> 0 | G37: =F37*8/100 -> 0 | H37: =F37-G37 -> 0 | I37: =(20%*H37)+200000 -> 200000 | J37: =SUM(I37:I37) -> 200000 | K37: =F37-J37 -> -200000 | L37: =L36 -> 0.07 | M37: =IF(K37-300000>0,'Tax Table - DONT ALTER'!D117,K37)*L37 -> -14000 | N37: =N36 -> 0.11 | O37: =IF(K37-600000>0,'Tax Table - DONT ALTER'!F117,K37-300000)*N37 -> -55000 | P37: =P36 -> 0.15 | Q37: =IF(K37-1100000>0,'Tax Table - DONT ALTER'!H118,K37-600000)*P37 -> -120000 | R37: =R36 -> 0.19 | S37: =IF(K37-1600000>0,'Tax Table - DONT ALTER'!J117,K37-1100000)*R37 -> -247000 | T37: =T36 -> 0.21 | U37: =IF(K37-3200000>0,'Tax Table - DONT ALTER'!L117,K37-1600000)*T37 -> -378000 | V37: =V36 -> 0.24 | W37: =IF(K37-3200000>0,K37-3200000)*V37 -> 0 | X37: =1%*F37 -> 0 | Y37: =IF(M37>=0,M37)+IF(O37>=0,O37)+IF(Q37>=0,Q37)+IF(S37>=0,S37)+IF(U37>=0,U37)+IF(W37>=0,W37) -> 0 | Z37: =F37-G37-H37-Y37 -> 0 | AA37: =Z37/12 -> 0 | AC37: =AB37/12 -> 0 | AE37: =AD37/12 -> 0 | AG37: =AF37/12 -> 0 | AH37: =AD37+AF37 -> 0 | AI37: =AE37+AG37 -> 0
F38: =SUM(F8:F37) -> 9654177.8 | G38: =SUM(G9:G37) -> 772334.23 | I38: =SUM(I9:I37) -> 7576368.7 | J38: =SUM(J9:J37) -> 7576368.7 | K38: =SUM(K9:K37) -> 1305474.9 | X38: =SUM(X9:X37) -> 96541.778 | Y38: =SUM(Y9:Y37) -> 1070843.7 | Z38: =SUM(Z9:Z37) -> 7810999.9 | AA38: =SUM(AA9:AA37) -> 650916.66 | AB38: =SUM(AB9:AB37) -> 1070843.7 | AC38: =SUM(AC9:AC37) -> 89236.975 | AD38: =SUM(AD9:AD37) -> 772334.23 | AE38: =SUM(AE9:AE37) -> 64361.186 | ... AI38: =SUM(AI9:AI37) -> 120360.5

Sheet Tax Table - DONT ALTER
C5: IST N300,000 | D5: 300000 | E5: NEXT N300,000 | F5: 300000 | G5: NEXT N500,000 | H5: 500000 | I5: NEXT N500,000 | J5: 500000 | K5: NEXT N1,600,000 | L5: 1600000 | M5: ABOVE N3,200,000 | N5: 3200000
D6: 300000 | F6: 300000 | H6: 500000 | J6: 500000 | L6: 1600000 | N6: 3200000
D7: 300000 | F7: 300000 | H7: 500000 | J7: 500000 | L7: 1600000 | N7: 3200000
D8: 300000 | F8: 300000 | H8: 500000 | J8: 500000 | L8: 1600000 | N8: 3200000
D9: 300000 | F9: 300000 | H9: 500000 | J9: 500000 | L9: 1600000 | N9: 3200000
D10: 300000 | F10: 300000 | H10: 500000 | J10: 500000 | L10: 1600000 | N10: 3200000
D11: 300000 | F11: 300000 | H11: 500000 | J11: 500000 | L11: 1600000 | N11: 3200000
D12: 300000 | F12: 300000 | H12: 500000 | J12: 500000 | L12: 1600000 | N12: 3200000
D13: 300000 | F13: 300000 | H13: 500000 | J13: 500000 | L13: 1600000 | N13: 3200000
D14: 300000 | F14: 300000 | H14: 500000 | J14: 500000 | L14: 1600000 | N14: 3200000
D15: 300000 | F15: 300000 | H15: 500000 | J15: 500000 | L15: 1600000 | N15: 3200000
D16: 300000 | F16: 300000 | H16: 500000 | J16: 500000 | L16: 1600000 | N16: 3200000
D17: 300000 | F17: 300000 | H17: 500000 | J17: 500000 | L17: 1600000 | N17: 3200000
... D745: 300000 | F745: 300000 | H745: 500000 | J745: 500000 | L745: 1600000 | N745: 3200000

Sheet 5_Payslip
C3: Name
C4: Staff Code
C5: Location
C6: Designation
C8: Month
C9: Year | D9: 2022
B11: Description | C11: N | D11: N
B13: (A) Components of Salary
B14: Basic Salary
B15: Housing Allowance
B16: Transport Allowance
B17: Personal Pay Leave Allowance
B18: Perfomance Linked Incentive
B22: Gross Remuneration | C22: =SUM(C14:C21) -> 0 | D22: =C22 -> 0
B23: (B) Other Benefits | C23: -
B24: Less: Deductions
B25: Non-Statutory
B26: Lateness
B27: Loan
B28: Total Non-Statutory Deductions | C28: =SUM(C26:C27) -> 0 | D28: =-C28 -> 0
B30: Statutory Deductions
B31: PAYE
B32: Pension
B33: NHIS | C33: -
B34: NSITF | C34: -
B35: Total Statutory Deductions | C35: =SUM(C31:C34) -> 0 | D35: =-C35 -> 0
B38: Net Pay | D38: =SUM(D22:D35) -> 0
B40: Prepared by: | D40: Approved by:
B41: Name: | D41: Name:
B42: Designation: | D42: Designation:
B43: Date | D43: Date
B44: Signature | D44: Signature

Sheet 6_Payslip
C3: Name
C4: Staff Code
C5: Location
C6: Designation
C8: Month
C9: Year
B11: Description | C11: N | D11: N
B13: (A) Components of Salary
B14: Basic Salary
B15: Housing Allowance
B16: Transport Allowance
B17: Personal Pay Leave Allowance
B18: Perfomance Linked Incentive
B22: Gross Remuneration | C22: =SUM(C14:C21) -> 0 | D22: =C22 -> 0
B23: (B) Other Benefits | C23: -
B24: Less: Deductions
B25: Non-Statutory
B26: Lateness
B27: Loan
B28: Total Non-Statutory Deductions | C28: =SUM(C26:C27) -> 0 | D28: =-C28 -> 0
B30: Statutory Deductions
B31: PAYE
B32: Pension
B33: NHIS
B34: NSITF
B35: Total Statutory Deductions | C35: =SUM(C31:C34) -> 0 | D35: =-C35 -> 0
B38: Net Pay | D38: =SUM(D22:D35) -> 0
B40: Prepared by: | D40: Approved by:
B41: Name: | D41: Name:
B42: Designation: | D42: Designation:
B43: Date | D43: Date
B44: Signature | D44: Signature

Sheet 7_Payslip
C3: Name
C4: Staff Code
C5: Location
C6: Designation
C8: Month
C9: Year
B11: Description | C11: N | D11: N
B13: (A) Components of Salary
B14: Basic Salary
B15: Housing Allowance
B16: Transport Allowance
B17: Personal Pay Leave Allowance
B18: Perfomance Linked Incentive
B22: Gross Remuneration | C22: =SUM(C14:C21) -> 0 | D22: =C22 -> 0
B23: (B) Other Benefits | C23: -
B24: Less: Deductions
B25: Non-Statutory
B26: Lateness
B27: Loan
B28: Total Non-Statutory Deductions | C28: =SUM(C26:C27) -> 0 | D28: =-C28 -> 0
B30: Statutory Deductions
B31: PAYE
B32: Pension
B33: NHIS | C33: -
B34: NSITF | C34: -
B35: Total Statutory Deductions | C35: =SUM(C31:C34) -> 0 | D35: =-C35 -> 0
B38: Net Pay | D38: =SUM(D22:D35) -> 0
B40: Prepared by: | D40: Approved by:
B41: Name: | D41: Name:
B42: Designation: | D42: Designation:
B43: Date | D43: Date
B44: Signature | D44: Signature

Sheet 8_Payslip
C3: Name
C4: Staff Code
C5: Location
C6: Designation
C8: Month
C9: Year
B11: Description | C11: N | D11: N
B13: (A) Components of Salary
B14: Basic Salary
B15: Housing Allowance
B16: Transport Allowance
B17: Personal Pay Leave Allowance
B18: Perfomance Linked Incentive
B22: Gross Remuneration | C22: =SUM(C14:C21) -> 0 | D22: =C22 -> 0
B23: (B) Other Benefits | C23: -
B24: Less: Deductions
B25: Non-Statutory
B26: Lateness
B27: Loan
B28: Total Non-Statutory Deductions | C28: =SUM(C26:C27) -> 0 | D28: =-C28 -> 0
B30: Statutory Deductions
B31: PAYE
B32: Pension
B33: NHIS | C33: -
B34: NSITF | C34: -
B35: Total Statutory Deductions | C35: =SUM(C31:C34) -> 0 | D35: =-C35 -> 0
B38: Net Pay | D38: =SUM(D22:D35) -> 0
B40: Prepared by: | D40: Approved by:
B41: Name: | D41: Name:
B42: Designation: | D42: Designation:
B43: Date | D43: Date
B44: Signature | D44: Signature

Sheet 9_Payslip
C3: Name
C4: Staff Code
C5: Location
C6: Designation
C8: Month
C9: Year
B11: Description | C11: N | D11: N
B13: (A) Components of Salary
B14: Basic Salary
B15: Housing Allowance
B16: Transport Allowance
B17: Personal Pay Leave Allowance
B18: Perfomance Linked Incentive
B22: Gross Remuneration | C22: =SUM(C14:C21) -> 0 | D22: =C22 -> 0
B23: (B) Other Benefits | C23: -
B24: Less: Deductions
B25: Non-Statutory
B26: Lateness
B27: Loan
B28: Total Non-Statutory Deductions | C28: =SUM(C26:C27) -> 0 | D28: =-C28 -> 0
B30: Statutory Deductions
B31: PAYE
B32: Pension
B33: NHIS
B34: NSITF
B35: Total Statutory Deductions | C35: =SUM(C31:C34) -> 0 | D35: =-C35 -> 0
B38: Net Pay | D38: =SUM(D22:D35) -> 0
B40: Prepared by: | D40: Approved by:
B41: Name: | D41: Name:
B42: Designation: | D42: Designation:
B43: Date | D43: Date
B44: Signature | D44: Signature

Sheet 10_Payslip
C3: Name
C4: Staff Code
C5: Location
C6: Designation
C8: Month
C9: Year
B11: Description | C11: N | D11: N
B13: (A) Components of Salary
B14: Basic Salary
B15: Housing Allowance
B16: Transport Allowance
B17: Personal Pay Leave Allowance
B18: Perfomance Linked Incentive
B22: Gross Remuneration | C22: =SUM(C14:C21) -> 0 | D22: =C22 -> 0
B23: (B) Other Benefits | C23: -
B24: Less: Deductions
B25: Non-Statutory
B26: Lateness
B27: Loan
B28: Total Non-Statutory Deductions | C28: =SUM(C26:C27) -> 0 | D28: =-C28 -> 0
B30: Statutory Deductions
B31: PAYE
B32: Pension
B33: NHIS
B34: NSITF
B35: Total Statutory Deductions | C35: =SUM(C31:C34) -> 0 | D35: =-C35 -> 0
B38: Net Pay | D38: =SUM(D22:D35) -> 0
B40: Prepared by: | D40: Approved by:
B41: Name: | D41: Name:
B42: Designation: | D42: Designation:
B43: Date | D43: Date
B44: Signature | D44: Signature
